dreem/__init__.py
dreem/_version.py
dreem/cli.py
dreem/configs/defaults/track.yaml
dreem/configs/defaults/train.yaml
dreem/datasets/__init__.py
dreem/datasets/base_dataset.py
dreem/datasets/cell_tracking_dataset.py
dreem/datasets/data_utils.py
dreem/datasets/microscopy_dataset.py
dreem/datasets/preprocessors.py
dreem/datasets/sleap_dataset.py
dreem/datasets/tracking_dataset.py
dreem/inference/__init__.py
dreem/inference/boxes.py
dreem/inference/eval.py
dreem/inference/metrics.py
dreem/inference/post_processing.py
dreem/inference/post_processing_utils.py
dreem/inference/track.py
dreem/inference/track_queue.py
dreem/inference/tracker.py
dreem/io/__init__.py
dreem/io/association_matrix.py
dreem/io/config.py
dreem/io/flags.py
dreem/io/frame.py
dreem/io/instance.py
dreem/io/track.py
dreem/io/visualize.py
dreem/models/__init__.py
dreem/models/attention_head.py
dreem/models/embedding.py
dreem/models/global_tracking_transformer.py
dreem/models/gtr_runner.py
dreem/models/mlp.py
dreem/models/model_utils.py
dreem/models/transformer.py
dreem/models/visual_encoder.py
dreem/training/__init__.py
dreem/training/losses.py
dreem/training/train.py
dreem/utils/__init__.py
dreem/utils/processors.py
dreem_track-0.2.0.dist-info/METADATA
dreem_track-0.2.0.dist-info/WHEEL
dreem_track-0.2.0.dist-info/entry_points.txt
dreem_track-0.2.0.dist-info/licenses/LICENSE
dreem_track-0.2.0.dist-info/RECORD
