Metadata-Version: 2.4
Name: dreem-track
Version: 0.2.0
Summary: Global Tracking Transformers for biological multi-object tracking.
Project-URL: Homepage, https://github.com/talmolab/dreem
Project-URL: Repository, https://github.com/talmolab/dreem
Author-email: Arlo Sheridan <asheridan@salk.edu>, Aaditya Prasad <aprasad@salk.edu>, Vincent Tu <vtu@ucsd.edu>, Uri Manor <umanor@salk.edu>, Talmo Pereira <talmo@salk.edu>
License: BSD-3-Clause
License-File: LICENSE
Keywords: deep learning,gtr,mot,tracking,transformers
Classifier: Development Status :: 4 - Beta
Classifier: Intended Audience :: Science/Research
Classifier: License :: OSI Approved :: BSD License
Classifier: Programming Language :: Python :: 3.12
Classifier: Topic :: Scientific/Engineering :: Artificial Intelligence
Requires-Python: >=3.12
Requires-Dist: albumentations
Requires-Dist: av
Requires-Dist: huggingface-hub
Requires-Dist: hydra-core
Requires-Dist: imageio-ffmpeg
Requires-Dist: imageio>=2.34.0
Requires-Dist: lightning
Requires-Dist: matplotlib
Requires-Dist: motmetrics
Requires-Dist: numpy<2.0
Requires-Dist: opencv-python<4.9.0
Requires-Dist: rich>=13.0.0
Requires-Dist: seaborn
Requires-Dist: sleap-io
Requires-Dist: timm
Requires-Dist: torch>=2.0.0
Requires-Dist: torchvision
Requires-Dist: typer>=0.12.0
Requires-Dist: wandb
Provides-Extra: encoder
Requires-Dist: scikit-image; extra == 'encoder'
